Metadata-Version: 2.4
Name: nonebot-plugin-paocha
Version: 2.0.0
Summary: 这是一个用于群内泡茶，签到的nonebot插件
Author-email: mmxd12 <2529464880@qq.com>
License: MIT
Classifier: License :: OSI Approved :: MIT License
Classifier: Operating System :: OS Independent
Classifier: Programming Language :: Python :: 3.9
Classifier: Programming Language :: Python :: 3.10
Classifier: Programming Language :: Python :: 3.11
Classifier: Programming Language :: Python :: 3.12
Requires-Python: >=3.9
License-File: LICENSE
Requires-Dist: nonebot2>=2.0.0
Requires-Dist: nonebot-adapter-qq>=1.6.5
Requires-Dist: httpx>=0.28.1
Dynamic: license-file
